toolify/__init__.py
toolify/tools-old.py
toolify/tools.py
toolify-0.2.0.dist-info/licenses/LICENSE
toolify-0.2.0.dist-info/METADATA
toolify-0.2.0.dist-info/WHEEL
toolify-0.2.0.dist-info/top_level.txt
toolify-0.2.0.dist-info/RECORD
