Metadata-Version: 2.4
Name: toolify
Version: 0.2.0
Summary: A library that provide helper function and tools.
Author: Amr Abdelsamea
Author-email: amr.abdelsamee33@gmail.com
License: MIT
Keywords: tools,arabic,bidi,plotting,logging,cuda
Classifier: Programming Language :: Python :: 3
Classifier: Programming Language :: Python :: 3.8
Classifier: Programming Language :: Python :: 3.9
Classifier: Programming Language :: Python :: 3.10
Classifier: Programming Language :: Python :: 3.11
Classifier: Programming Language :: Python :: 3.12
Classifier: License :: OSI Approved :: MIT License
Classifier: Operating System :: OS Independent
Requires-Python: >=3.8
License-File: LICENSE
Requires-Dist: python-bidi==0.6.6
Requires-Dist: arabic_reshaper==3.0.0
Dynamic: author
Dynamic: author-email
Dynamic: classifier
Dynamic: description
Dynamic: description-content-type
Dynamic: keywords
Dynamic: license
Dynamic: license-file
Dynamic: requires-dist
Dynamic: requires-python
Dynamic: summary
